setup.cfg
setup.py
bluebutton/__init__.py
bluebutton.egg-info/PKG-INFO
bluebutton.egg-info/SOURCES.txt
bluebutton.egg-info/dependency_links.txt
bluebutton.egg-info/top_level.txt
bluebutton/core/__init__.py
bluebutton/core/_core.py
bluebutton/core/codes.py
bluebutton/core/wrappers.py
bluebutton/core/xml.py
bluebutton/documents/__init__.py
bluebutton/documents/ccda.py
bluebutton/parsers/__init__.py
bluebutton/parsers/ccda.py
bluebutton/parsers/_ccda/__init__.py
bluebutton/parsers/_ccda/allergies.py
bluebutton/parsers/_ccda/care_plan.py
bluebutton/parsers/_ccda/demographics.py
bluebutton/parsers/_ccda/document.py
bluebutton/parsers/_ccda/encounters.py
bluebutton/parsers/_ccda/free_text.py
bluebutton/parsers/_ccda/functional_statuses.py
bluebutton/parsers/_ccda/immunizations.py
bluebutton/parsers/_ccda/instructions.py
bluebutton/parsers/_ccda/medications.py
bluebutton/parsers/_ccda/problems.py
bluebutton/parsers/_ccda/procedures.py
bluebutton/parsers/_ccda/results.py
bluebutton/parsers/_ccda/smoking_status.py
bluebutton/parsers/_ccda/vitals.py