Metadata-Version: 1.0
Name: bluebutton
Version: 0.3.0.post1
Summary: The Blue Button Python Library
Home-page: https://github.com/ctsit/bluebutton.py
Author: Taeber Rapczak
Author-email: taeber@ufl.edu
License: Apache License, Version 2.0
Keywords: bb,blue button,ccda,c-cda,ehr,emr,health,healthcare,medical,phr,record
Platform: UNKNOWN
